nutellaC/__init__.py
nutellaC/nutellaRequests.py
nutellaC/nutellaSdk.py
nutellaC-0.1.dist-info/METADATA
nutellaC-0.1.dist-info/WHEEL
nutellaC-0.1.dist-info/top_level.txt
nutellaC-0.1.dist-info/RECORD
