Metadata-Version: 2.1
Name: nutellaC
Version: 0.1
Summary: for nutella service
Home-page: https://github.com/song-o/pypi_practice.git
Author: songpie
Author-email: songmi.ohh@gmail.com
License: UNKNOWN
Keywords: nutellaC
Platform: UNKNOWN
Classifier: Programming Language :: Python :: 3
Classifier: Programming Language :: Python :: 3.2
Classifier: Programming Language :: Python :: 3.3
Classifier: Programming Language :: Python :: 3.4
Classifier: Programming Language :: Python :: 3.5
Classifier: Programming Language :: Python :: 3.6
Classifier: Programming Language :: Python :: 3.7
Requires-Python: >=3
